./.gitignore
./LICENSE
./PKG-INFO
./README.md
./epss_api.py
./epss_mcp.py
./nvd_api.py
./pyproject.toml
iflow_mcp_jgamblin_epss_mcp-0.1.0.dist-info/METADATA
iflow_mcp_jgamblin_epss_mcp-0.1.0.dist-info/WHEEL
iflow_mcp_jgamblin_epss_mcp-0.1.0.dist-info/entry_points.txt
iflow_mcp_jgamblin_epss_mcp-0.1.0.dist-info/licenses/LICENSE
iflow_mcp_jgamblin_epss_mcp-0.1.0.dist-info/RECORD
