Metadata-Version: 2.4
Name: iflow-mcp_jgamblin_epss-mcp
Version: 0.1.0
Summary: EPSS MCP Server - Retrieve CVE details and EPSS scores
License-File: LICENSE
Requires-Python: >=3.11
Requires-Dist: fastapi
Requires-Dist: httpx
Requires-Dist: mcp>=1.0.0
Requires-Dist: pydantic
Requires-Dist: python-dotenv
Requires-Dist: uvicorn
